cgnxpyairpal/__init__.py
cgnxpyairpal-1.0.0.dist-info/METADATA
cgnxpyairpal-1.0.0.dist-info/RECORD
cgnxpyairpal-1.0.0.dist-info/WHEEL
cgnxpyairpal-1.0.0.dist-info/top_level.txt
