Metadata-Version: 2.1
Name: cgnxpyairpal
Version: 1.0.0
Summary: Python Client/SDK for Airpal
Home-page: https://github.com/YugeshBhosale-GSLab/cgnxpyairpal
Author: Yugesh Bhosale
Author-email: yugesh.bhosale@gslab.com
License: MIT
Platform: UNKNOWN
Classifier: Development Status :: 5 - Production/Stable
Classifier: Intended Audience :: Developers
Classifier: License :: OSI Approved :: MIT License
Classifier: Programming Language :: Python :: 2.7
Classifier: Programming Language :: Python :: 3
Requires-Dist: requests (>=2.18.4)
Requires-Dist: sseclient (>=0.0.18)
